muke/Lines.py
muke/Muke.py
muke/__init__.py
muke/__main__.py
muke/detector/BaseDetector.py
muke/detector/KeyPoint2.py
muke/detector/MediaPipeFaceDetector.py
muke/detector/MediaPipePoseDetector.py
muke/detector/MediaPiperBaseDetector.py
muke/detector/__init__.py
muke/generator/BaseGenerator.py
muke/generator/Wrap3Generator.py
muke/generator/__init__.py
muke/model/DetectionView.py
muke/model/KeyPoint3.py
muke/model/MukeConfiguration.py
muke/model/Vertex.py
muke/model/__init__.py
muke/rendering/BaseRenderer.py
muke/rendering/GfxRenderer.py
muke/rendering/__init__.py
muke/rendering/gfx_utils.py
muke-0.3.5.4.dist-info/LICENSE
muke-0.3.5.4.dist-info/METADATA
muke-0.3.5.4.dist-info/WHEEL
muke-0.3.5.4.dist-info/entry_points.txt
muke-0.3.5.4.dist-info/top_level.txt
muke-0.3.5.4.dist-info/RECORD
