Metadata-Version: 2.1
Name: muke
Version: 0.3.5.4
Summary: A simple approach to 3D keypoint detection using 2D estimation methods and multiview rendering.
Home-page: https://github.com/cansik/multiview-3d-keypoint-detection
Author: Florian Bruggisser
Author-email: github@broox.ch
License: MIT License
Platform: UNKNOWN
License-File: LICENSE
Requires-Dist: wheel
Requires-Dist: numpy
Requires-Dist: open3d >=0.16.0
Requires-Dist: opencv-python
Requires-Dist: tqdm
Requires-Dist: scipy
Requires-Dist: pygfx ~=0.1.18.0
Requires-Dist: trimesh ~=4.1.0
Requires-Dist: mediapipe
